splitutils/__init__.py
splitutils/core/__init__.py
splitutils/core/splitutils.py
splitutils-0.4.3.dist-info/licenses/LICENSE
splitutils-0.4.3.dist-info/METADATA
splitutils-0.4.3.dist-info/WHEEL
splitutils-0.4.3.dist-info/top_level.txt
splitutils-0.4.3.dist-info/RECORD
