Metadata-Version: 2.4
Name: splitutils
Version: 0.4.3
Summary: Group disjunct and stratified data splits
Home-page: https://github.com/reichelu/splitutils
Author: Uwe Reichel
Author-email: ureichel@audeering.com
Project-URL: repository, https://github.com/reichelu/splitutils
Project-URL: documentation, https://github.com/reichelu/splitutils
Project-URL: company, https://www.audeering.com/
Classifier: Programming Language :: Python :: 3
Classifier: License :: OSI Approved :: MIT License
Classifier: Operating System :: OS Independent
Classifier: Development Status :: 4 - Beta
Classifier: Topic :: Scientific/Engineering
Requires-Python: >=3.10
License-File: LICENSE
Requires-Dist: numpy
Requires-Dist: pandas
Requires-Dist: scipy
Requires-Dist: scikit-learn
Dynamic: license-file
